{
	"$schema": "http://schema.management.azure.com/schemas/2015-01-01/deploymentTemplate.json#",
	"contentVersion": "1.0.0.0",
	"parameters": {
		"factoryName": {
			"type": "string",
			"metadata": "Data Factory name",
			"defaultValue": "DF-ADEBATCH22a"
		},
		"LS_adls_connectionString": {
			"type": "secureString",
			"metadata": "Secure string for 'connectionString' of 'LS_adls'"
		},
		"LS_sql_password": {
			"type": "secureString",
			"metadata": "Secure string for 'password' of 'LS_sql'"
		},
		"LS_sql_param_password": {
			"type": "secureString",
			"metadata": "Secure string for 'password' of 'LS_sql_param'"
		},
		"KV_azure_properties_typeProperties_baseUrl": {
			"type": "string",
			"defaultValue": "https://kvault-adebatch22.vault.azure.net/"
		},
		"LS_sql_properties_typeProperties_server": {
			"type": "string",
			"defaultValue": "sqlserver-adebatch22a.database.windows.net"
		},
		"LS_sql_properties_typeProperties_database": {
			"type": "string",
			"defaultValue": "sqldb_adebatch22"
		},
		"LS_sql_properties_typeProperties_userName": {
			"type": "string",
			"defaultValue": "adebatch22"
		},
		"LS_sql_param_properties_typeProperties_server": {
			"type": "string",
			"defaultValue": "@{linkedService().server_name}"
		},
		"LS_sql_param_properties_typeProperties_database": {
			"type": "string",
			"defaultValue": "@{linkedService().db_name}"
		},
		"LS_sql_param_properties_typeProperties_userName": {
			"type": "string",
			"defaultValue": "adebatch22"
		}
	},
	"variables": {
		"factoryId": "[concat('Microsoft.DataFactory/factories/', parameters('factoryName'))]"
	},
	"resources": [
		{
			"name": "[concat(parameters('factoryName'), '/IF-condition')]",
			"type": "Microsoft.DataFactory/factories/pipelines",
			"apiVersion": "2018-06-01",
			"properties": {
				"activities": [
					{
						"name": "If Condition1",
						"type": "IfCondition",
						"dependsOn": [],
						"userProperties": [],
						"typeProperties": {
							"expression": {
								"value": "false",
								"type": "Expression"
							},
							"ifFalseActivities": [
								{
									"name": "Wait_false",
									"type": "Wait",
									"dependsOn": [],
									"userProperties": [],
									"typeProperties": {
										"waitTimeInSeconds": 1
									}
								}
							],
							"ifTrueActivities": [
								{
									"name": "Wait_true",
									"type": "Wait",
									"dependsOn": [],
									"userProperties": [],
									"typeProperties": {
										"waitTimeInSeconds": 1
									}
								}
							]
						}
					}
				],
				"policy": {
					"elapsedTimeMetric": {}
				},
				"annotations": [],
				"lastPublishTime": "2025-03-25T14:29:44Z"
			},
			"dependsOn": []
		},
		{
			"name": "[concat(parameters('factoryName'), '/Lemon')]",
			"type": "Microsoft.DataFactory/factories/pipelines",
			"apiVersion": "2018-06-01",
			"properties": {
				"activities": [
					{
						"name": "Wait1",
						"type": "Wait",
						"dependsOn": [],
						"userProperties": [],
						"typeProperties": {
							"waitTimeInSeconds": 2000
						}
					}
				],
				"policy": {
					"elapsedTimeMetric": {}
				},
				"annotations": []
			},
			"dependsOn": []
		},
		{
			"name": "[concat(parameters('factoryName'), '/emp2_pipeline')]",
			"type": "Microsoft.DataFactory/factories/pipelines",
			"apiVersion": "2018-06-01",
			"properties": {
				"activities": [
					{
						"name": "Wait1",
						"type": "Wait",
						"dependsOn": [],
						"userProperties": [],
						"typeProperties": {
							"waitTimeInSeconds": 60
						}
					}
				],
				"policy": {
					"elapsedTimeMetric": {}
				},
				"annotations": []
			},
			"dependsOn": []
		},
		{
			"name": "[concat(parameters('factoryName'), '/foreach_static')]",
			"type": "Microsoft.DataFactory/factories/pipelines",
			"apiVersion": "2018-06-01",
			"properties": {
				"activities": [
					{
						"name": "ForEach1",
						"type": "ForEach",
						"dependsOn": [],
						"userProperties": [],
						"typeProperties": {
							"items": {
								"value": "@pipeline().parameters.input_file",
								"type": "Expression"
							},
							"activities": [
								{
									"name": "Wait1",
									"type": "Wait",
									"dependsOn": [],
									"userProperties": [],
									"typeProperties": {
										"waitTimeInSeconds": 1
									}
								}
							]
						}
					}
				],
				"policy": {
					"elapsedTimeMetric": {}
				},
				"parameters": {
					"input_file": {
						"type": "array",
						"defaultValue": [
							1,
							2,
							3
						]
					}
				},
				"annotations": [],
				"lastPublishTime": "2025-03-25T06:23:12Z"
			},
			"dependsOn": []
		},
		{
			"name": "[concat(parameters('factoryName'), '/new_schedule')]",
			"type": "Microsoft.DataFactory/factories/pipelines",
			"apiVersion": "2018-06-01",
			"properties": {
				"activities": [
					{
						"name": "Wait1",
						"type": "Wait",
						"dependsOn": [],
						"userProperties": [],
						"typeProperties": {
							"waitTimeInSeconds": 1
						}
					}
				],
				"policy": {
					"elapsedTimeMetric": {}
				},
				"annotations": [],
				"lastPublishTime": "2025-04-04T11:09:58Z"
			},
			"dependsOn": []
		},
		{
			"name": "[concat(parameters('factoryName'), '/schedule_pipeline_1')]",
			"type": "Microsoft.DataFactory/factories/pipelines",
			"apiVersion": "2018-06-01",
			"properties": {
				"activities": [
					{
						"name": "Wait1",
						"type": "Wait",
						"dependsOn": [],
						"userProperties": [],
						"typeProperties": {
							"waitTimeInSeconds": 1
						}
					}
				],
				"policy": {
					"elapsedTimeMetric": {}
				},
				"annotations": [],
				"lastPublishTime": "2025-04-04T11:01:25Z"
			},
			"dependsOn": []
		},
		{
			"name": "[concat(parameters('factoryName'), '/set_append_var')]",
			"type": "Microsoft.DataFactory/factories/pipelines",
			"apiVersion": "2018-06-01",
			"properties": {
				"activities": [
					{
						"name": "Append variable1",
						"type": "AppendVariable",
						"dependsOn": [
							{
								"activity": "Set variable1",
								"dependencyConditions": [
									"Succeeded"
								]
							}
						],
						"userProperties": [],
						"typeProperties": {
							"variableName": "final_list",
							"value": {
								"value": "@variables('set_var1')",
								"type": "Expression"
							}
						}
					},
					{
						"name": "Set variable1",
						"type": "SetVariable",
						"dependsOn": [],
						"policy": {
							"secureOutput": false,
							"secureInput": false
						},
						"userProperties": [],
						"typeProperties": {
							"variableName": "set_var1",
							"value": "madhuri"
						}
					},
					{
						"name": "Set variable1_copy1",
						"type": "SetVariable",
						"dependsOn": [
							{
								"activity": "Append variable1",
								"dependencyConditions": [
									"Succeeded"
								]
							}
						],
						"policy": {
							"secureOutput": false,
							"secureInput": false
						},
						"userProperties": [],
						"typeProperties": {
							"variableName": "set_var1",
							"value": "ramya"
						}
					},
					{
						"name": "Append variable1_copy1",
						"type": "AppendVariable",
						"dependsOn": [
							{
								"activity": "Set variable1_copy1",
								"dependencyConditions": [
									"Succeeded"
								]
							}
						],
						"userProperties": [],
						"typeProperties": {
							"variableName": "final_list",
							"value": {
								"value": "@variables('set_var1')",
								"type": "Expression"
							}
						}
					},
					{
						"name": "Set variable2",
						"type": "SetVariable",
						"dependsOn": [
							{
								"activity": "Append variable1_copy1",
								"dependencyConditions": [
									"Succeeded"
								]
							}
						],
						"policy": {
							"secureOutput": false,
							"secureInput": false
						},
						"userProperties": [],
						"typeProperties": {
							"variableName": "append_final_list",
							"value": {
								"value": "@variables('final_list')",
								"type": "Expression"
							}
						}
					}
				],
				"policy": {
					"elapsedTimeMetric": {}
				},
				"variables": {
					"set_var1": {
						"type": "String",
						"defaultValue": "madhuri"
					},
					"final_list": {
						"type": "Array"
					},
					"append_final_list": {
						"type": "Array"
					},
					"list_of_files": {
						"type": "Array"
					},
					"append_lis": {
						"type": "Array"
					}
				},
				"annotations": [],
				"lastPublishTime": "2025-04-04T08:31:55Z"
			},
			"dependsOn": []
		},
		{
			"name": "[concat(parameters('factoryName'), '/switch_activity')]",
			"type": "Microsoft.DataFactory/factories/pipelines",
			"apiVersion": "2018-06-01",
			"properties": {
				"activities": [
					{
						"name": "Switch1",
						"type": "Switch",
						"dependsOn": [],
						"userProperties": [],
						"typeProperties": {
							"on": {
								"value": "Folder",
								"type": "Expression"
							},
							"cases": [
								{
									"value": "Folder1",
									"activities": [
										{
											"name": "Wait_folder1",
											"type": "Wait",
											"dependsOn": [],
											"userProperties": [],
											"typeProperties": {
												"waitTimeInSeconds": 1
											}
										}
									]
								},
								{
									"value": "Folder2",
									"activities": [
										{
											"name": "Wait_folder2",
											"type": "Wait",
											"dependsOn": [],
											"userProperties": [],
											"typeProperties": {
												"waitTimeInSeconds": 1
											}
										}
									]
								}
							],
							"defaultActivities": [
								{
									"name": "Wait_false",
									"type": "Wait",
									"dependsOn": [],
									"userProperties": [],
									"typeProperties": {
										"waitTimeInSeconds": 1
									}
								}
							]
						}
					}
				],
				"policy": {
					"elapsedTimeMetric": {}
				},
				"variables": {
					"country": {
						"type": "String"
					}
				},
				"annotations": [],
				"lastPublishTime": "2025-03-26T07:57:23Z"
			},
			"dependsOn": []
		},
		{
			"name": "[concat(parameters('factoryName'), '/web')]",
			"type": "Microsoft.DataFactory/factories/pipelines",
			"apiVersion": "2018-06-01",
			"properties": {
				"activities": [
					{
						"name": "Web1",
						"type": "WebActivity",
						"dependsOn": [],
						"policy": {
							"timeout": "0.12:00:00",
							"retry": 0,
							"retryIntervalInSeconds": 30,
							"secureOutput": false,
							"secureInput": false
						},
						"userProperties": [],
						"typeProperties": {
							"method": "GET",
							"headers": {},
							"url": "https://management.azure.com/subscriptions/8a44f555-6954-4a26-963a-bec606516adf/resourceGroups/ADE_Batch22/providers/Microsoft.DataFactory/factories/DF-secondary-batch22/pipelines/resapi/createRun?api-version=2018-06-01",
							"authentication": {
								"type": "MSI",
								"resource": "https://management.azure.com/"
							}
						}
					}
				],
				"policy": {
					"elapsedTimeMetric": {}
				},
				"annotations": [],
				"lastPublishTime": "2025-04-08T10:39:41Z"
			},
			"dependsOn": []
		},
		{
			"name": "[concat(parameters('factoryName'), '/webactivity')]",
			"type": "Microsoft.DataFactory/factories/pipelines",
			"apiVersion": "2018-06-01",
			"properties": {
				"activities": [
					{
						"name": "Web1",
						"type": "WebActivity",
						"dependsOn": [],
						"policy": {
							"timeout": "0.12:00:00",
							"retry": 0,
							"retryIntervalInSeconds": 30,
							"secureOutput": false,
							"secureInput": false
						},
						"userProperties": [],
						"typeProperties": {
							"method": "GET",
							"headers": {},
							"url": "https://reqres.in/api/users?page=2"
						}
					}
				],
				"policy": {
					"elapsedTimeMetric": {}
				},
				"annotations": [],
				"lastPublishTime": "2025-04-08T10:39:41Z"
			},
			"dependsOn": []
		},
		{
			"name": "[concat(parameters('factoryName'), '/KV_azure')]",
			"type": "Microsoft.DataFactory/factories/linkedServices",
			"apiVersion": "2018-06-01",
			"properties": {
				"annotations": [],
				"type": "AzureKeyVault",
				"typeProperties": {
					"baseUrl": "[parameters('KV_azure_properties_typeProperties_baseUrl')]"
				}
			},
			"dependsOn": []
		},
		{
			"name": "[concat(parameters('factoryName'), '/LS_adls')]",
			"type": "Microsoft.DataFactory/factories/linkedServices",
			"apiVersion": "2018-06-01",
			"properties": {
				"annotations": [],
				"type": "AzureBlobStorage",
				"typeProperties": {
					"connectionString": "[parameters('LS_adls_connectionString')]"
				}
			},
			"dependsOn": []
		},
		{
			"name": "[concat(parameters('factoryName'), '/LS_sql')]",
			"type": "Microsoft.DataFactory/factories/linkedServices",
			"apiVersion": "2018-06-01",
			"properties": {
				"annotations": [],
				"type": "AzureSqlDatabase",
				"typeProperties": {
					"server": "[parameters('LS_sql_properties_typeProperties_server')]",
					"database": "[parameters('LS_sql_properties_typeProperties_database')]",
					"encrypt": "mandatory",
					"trustServerCertificate": false,
					"authenticationType": "SQL",
					"userName": "[parameters('LS_sql_properties_typeProperties_userName')]",
					"password": {
						"type": "SecureString",
						"value": "[parameters('LS_sql_password')]"
					}
				}
			},
			"dependsOn": []
		},
		{
			"name": "[concat(parameters('factoryName'), '/LS_sql_param')]",
			"type": "Microsoft.DataFactory/factories/linkedServices",
			"apiVersion": "2018-06-01",
			"properties": {
				"parameters": {
					"server_name": {
						"type": "String"
					},
					"db_name": {
						"type": "string"
					}
				},
				"annotations": [],
				"type": "AzureSqlDatabase",
				"typeProperties": {
					"server": "[parameters('LS_sql_param_properties_typeProperties_server')]",
					"database": "[parameters('LS_sql_param_properties_typeProperties_database')]",
					"encrypt": "mandatory",
					"trustServerCertificate": false,
					"authenticationType": "SQL",
					"userName": "[parameters('LS_sql_param_properties_typeProperties_userName')]",
					"password": {
						"type": "SecureString",
						"value": "[parameters('LS_sql_param_password')]"
					}
				}
			},
			"dependsOn": []
		},
		{
			"name": "[concat(parameters('factoryName'), '/IR-India')]",
			"type": "Microsoft.DataFactory/factories/integrationRuntimes",
			"apiVersion": "2018-06-01",
			"properties": {
				"type": "Managed",
				"typeProperties": {
					"computeProperties": {
						"location": "AutoResolve",
						"dataFlowProperties": {
							"computeType": "General",
							"coreCount": 8,
							"timeToLive": 10,
							"cleanup": false,
							"customProperties": []
						}
					}
				}
			},
			"dependsOn": []
		},
		{
			"name": "[concat(parameters('factoryName'), '/Dataset_outputfloder')]",
			"type": "Microsoft.DataFactory/factories/datasets",
			"apiVersion": "2018-06-01",
			"properties": {
				"linkedServiceName": {
					"referenceName": "LS_adls",
					"type": "LinkedServiceReference"
				},
				"annotations": [],
				"type": "DelimitedText",
				"typeProperties": {
					"location": {
						"type": "AzureBlobStorageLocation",
						"folderPath": "Output",
						"container": "datasets"
					},
					"columnDelimiter": ",",
					"escapeChar": "\\",
					"firstRowAsHeader": true,
					"quoteChar": "\""
				},
				"schema": []
			},
			"dependsOn": [
				"[concat(variables('factoryId'), '/linkedServices/LS_adls')]"
			]
		},
		{
			"name": "[concat(parameters('factoryName'), '/cus1')]",
			"type": "Microsoft.DataFactory/factories/datasets",
			"apiVersion": "2018-06-01",
			"properties": {
				"linkedServiceName": {
					"referenceName": "LS_adls",
					"type": "LinkedServiceReference"
				},
				"annotations": [],
				"type": "DelimitedText",
				"typeProperties": {
					"location": {
						"type": "AzureBlobStorageLocation",
						"fileName": "Cus1.csv",
						"folderPath": "Input",
						"container": "datasets"
					},
					"columnDelimiter": ",",
					"escapeChar": "\\",
					"firstRowAsHeader": true,
					"quoteChar": "\""
				},
				"schema": []
			},
			"dependsOn": [
				"[concat(variables('factoryId'), '/linkedServices/LS_adls')]"
			]
		},
		{
			"name": "[concat(parameters('factoryName'), '/dataflow_output')]",
			"type": "Microsoft.DataFactory/factories/datasets",
			"apiVersion": "2018-06-01",
			"properties": {
				"linkedServiceName": {
					"referenceName": "LS_adls",
					"type": "LinkedServiceReference"
				},
				"annotations": [],
				"type": "DelimitedText",
				"typeProperties": {
					"location": {
						"type": "AzureBlobStorageLocation",
						"folderPath": "Output",
						"container": "dataflow"
					},
					"columnDelimiter": ",",
					"escapeChar": "\\",
					"firstRowAsHeader": true,
					"quoteChar": "\""
				},
				"schema": []
			},
			"dependsOn": [
				"[concat(variables('factoryId'), '/linkedServices/LS_adls')]"
			]
		},
		{
			"name": "[concat(parameters('factoryName'), '/dataset_input_folder')]",
			"type": "Microsoft.DataFactory/factories/datasets",
			"apiVersion": "2018-06-01",
			"properties": {
				"linkedServiceName": {
					"referenceName": "LS_adls",
					"type": "LinkedServiceReference"
				},
				"annotations": [],
				"type": "DelimitedText",
				"typeProperties": {
					"location": {
						"type": "AzureBlobStorageLocation",
						"folderPath": "Input",
						"container": "datasets"
					},
					"columnDelimiter": ",",
					"escapeChar": "\\",
					"firstRowAsHeader": true,
					"quoteChar": "\""
				},
				"schema": [
					{
						"name": "C.ID",
						"type": "String"
					},
					{
						"name": "FIRST_NAME",
						"type": "String"
					}
				]
			},
			"dependsOn": [
				"[concat(variables('factoryId'), '/linkedServices/LS_adls')]"
			]
		},
		{
			"name": "[concat(parameters('factoryName'), '/dept1_join')]",
			"type": "Microsoft.DataFactory/factories/datasets",
			"apiVersion": "2018-06-01",
			"properties": {
				"linkedServiceName": {
					"referenceName": "LS_adls",
					"type": "LinkedServiceReference"
				},
				"annotations": [],
				"type": "DelimitedText",
				"typeProperties": {
					"location": {
						"type": "AzureBlobStorageLocation",
						"fileName": "departments2.csv",
						"folderPath": "Input",
						"container": "dataflow"
					},
					"columnDelimiter": ",",
					"escapeChar": "\\",
					"firstRowAsHeader": true,
					"quoteChar": "\""
				},
				"schema": [
					{
						"name": "DEPARTMENT_ID",
						"type": "String"
					},
					{
						"name": "COUNTRY",
						"type": "String"
					},
					{
						"name": "DEPARTMENT_NAME",
						"type": "String"
					}
				]
			},
			"dependsOn": [
				"[concat(variables('factoryId'), '/linkedServices/LS_adls')]"
			]
		}
	]
}